README.md
fastcap.py
setup.py
fastcap.egg-info/PKG-INFO
fastcap.egg-info/SOURCES.txt
fastcap.egg-info/dependency_links.txt
fastcap.egg-info/requires.txt
fastcap.egg-info/top_level.txt