Metadata-Version: 1.0
Name: fastcap
Version: 0.1.1
Summary: fast screen cap on android, with minicap.
Home-page: https://github.com/williamfzc/fastcap
Author: williamfzc
Author-email: fengzc@vip.qq.com
License: UNKNOWN
Platform: UNKNOWN
